{
    "artist_name": "Cuco",
    "artist_link": "https://www.hooktheory.com/theorytab/artists/c/cuco",
    "song_name": "Feelings",
    "link": "https://www.hooktheory.com/theorytab/view/cuco/feelings",
    "metrics": {
        "Chord Complexity": "94",
        "Melodic Complexity": "42",
        "Chord-Melody Tension": "12",
        "Chord Progression Novelty": "52",
        "Chord Bass Melody": "12"
    },
    "metrics_conclusion": " Feelings has higher complexity than the average song  in terms Chord Complexity. ",
    "key_conclusion": " Feelings has sections analyzed in the following keys: D Minor,  and B♭ Minor.  Click on the linked cheat sheets for popular chords, chord progressions, downloadable midi files and more!",
    "song_parts_ids": [
        "dPoDvYnAgnM",
        "d_gwOzLrgGV"
    ]
}