{
    "artist_name": "Rush",
    "artist_link": "https://www.hooktheory.com/theorytab/artists/r/rush",
    "song_name": "Limelight",
    "link": "https://www.hooktheory.com/theorytab/view/rush/limelight",
    "metrics": {
        "Chord Complexity": "39",
        "Melodic Complexity": "27",
        "Chord-Melody Tension": "53",
        "Chord Progression Novelty": "53",
        "Chord Bass Melody": "79"
    },
    "metrics_conclusion": " Limelight has higher complexity than the average song  in terms Chord-Bass Melody. ",
    "key_conclusion": " Limelight has sections analyzed in the following keys: B Major,  and G♯ Minor.  Click on the linked cheat sheets for popular chords, chord progressions, downloadable midi files and more!",
    "song_parts_ids": [
        "yvgP_LlXmYq",
        "yvmrq-RzoOW"
    ]
}