{
    "artist_name": "Fiona Apple",
    "artist_link": "https://www.hooktheory.com/theorytab/artists/f/fiona-apple",
    "song_name": "Fast As You Can",
    "link": "https://www.hooktheory.com/theorytab/view/fiona-apple/fast-as-you-can",
    "metrics": {
        "Chord Complexity": "43",
        "Melodic Complexity": "13",
        "Chord-Melody Tension": "59",
        "Chord Progression Novelty": "47",
        "Chord Bass Melody": "74"
    },
    "metrics_conclusion": " Fast As You Can has higher complexity than the average song  in terms Chord-Bass Melody. ",
    "key_conclusion": " Fast As You Can has sections analyzed in the following keys: G Major,  and G Mixolydian.  Click on the linked cheat sheets for popular chords, chord progressions, downloadable midi files and more!",
    "song_parts_ids": [
        "ANmpq_XEgyM",
        "ROmNZJBjmNw",
        "zngRYpQMmJj",
        "YAg-BqMVxle"
    ]
}