{
    "artist_name": "Nataly Dawn",
    "artist_link": "https://www.hooktheory.com/theorytab/artists/n/nataly-dawn",
    "song_name": "Dying To Live",
    "link": "https://www.hooktheory.com/theorytab/view/nataly-dawn/dying-to-live",
    "metrics": {
        "Chord Complexity": "95",
        "Melodic Complexity": "44",
        "Chord-Melody Tension": "64",
        "Chord Progression Novelty": "94",
        "Chord Bass Melody": "80"
    },
    "metrics_conclusion": " In terms of chords and melody, Dying To Live is more complex than the typical song, having above average scores in Chord Complexity, Chord-Melody Tension, Chord Progression Novelty and Chord-Bass Melody. ",
    "key_conclusion": " Dying To Live is written in the key of A Major.  \n\nAccording to the Theorytab database, it is the 4th most popular key among Major keys and     the 4th most popular  among all keys. Major keys, along with minor keys, are a common choice for popular songs.  The three most important chords, built off the 1st, 4th and 5th scale degrees are all major chords (A Major, D Major, and E Major).\n\nSee the A Major Cheat Sheet for popular chords, chord progressions, downloadable midi files and more!",
    "song_parts_ids": [
        "_NgbWvzOxQA",
        "yvgPQWPExYq"
    ]
}