{
    "artist_name": "Bryan Scary",
    "artist_link": "https://www.hooktheory.com/theorytab/artists/b/bryan-scary",
    "song_name": "The Wicked Frontier",
    "link": "https://www.hooktheory.com/theorytab/view/bryan-scary/the-wicked-frontier",
    "metrics": {
        "Chord Complexity": "67",
        "Melodic Complexity": "80",
        "Chord-Melody Tension": "45",
        "Chord Progression Novelty": "79",
        "Chord Bass Melody": "23"
    },
    "metrics_conclusion": " The Wicked Frontier has higher complexity than the average song  in terms Chord Complexity, Melodic Complexity and Chord Progression Novelty. ",
    "key_conclusion": " The Wicked Frontier has sections analyzed in the following keys: G Major, C Minor,  and E♭ Major.  Click on the linked cheat sheets for popular chords, chord progressions, downloadable midi files and more!",
    "song_parts_ids": [
        "d_gwqqQboGV",
        "ANmpppWqmyM",
        "_NgbppkpoQA"
    ]
}