{
    "artist_name": "Oh Land",
    "artist_link": "https://www.hooktheory.com/theorytab/artists/o/oh-land",
    "song_name": "Helicopter",
    "link": "https://www.hooktheory.com/theorytab/view/oh-land/helicopter",
    "metrics": {
        "Chord Complexity": "63",
        "Melodic Complexity": "10",
        "Chord-Melody Tension": "12",
        "Chord Progression Novelty": "60",
        "Chord Bass Melody": "92"
    },
    "metrics_conclusion": " Helicopter has higher complexity than the average song  in terms Chord-Bass Melody. ",
    "key_conclusion": " Helicopter is written in the key of D♭ Major.  \n\nAccording to the Theorytab database, it is the 9th most popular key among Major keys and     the 16th most popular  among all keys. Major keys, along with minor keys, are a common choice for popular songs.  The three most important chords, built off the 1st, 4th and 5th scale degrees are all major chords (D♭ Major, G♭ Major, and A♭ Major).\n\nSee the D♭ Major Cheat Sheet for popular chords, chord progressions, downloadable midi files and more!",
    "song_parts": [
        {
            "song_part_id": "VMgJzQWEgqK",
            "metadata": {
                "ID": 223047,
                "user_id": 103696,
                "dateModified": "2015-11-04 14:35:29+00:00",
                "HTID": "ANiIyARZWJbu",
                "artist": "Oh Land",
                "song": "Helicopter",
                "section": "Verse",
                "revision": 0,
                "chords": null,
                "youTubeID": "SF8s8-6IXJM",
                "dotDNAbin": null,
                "xmlType": "file",
                "SIF": ",16-1.5,4-4.5,1-1,56-1,16-1.5,4-4.5,1-1,56-1,",
                "SInE": ",16-1.5,4-4.5,1-1,56-1,16-1.5,4-4.5,1-1,56-1,",
                "SInD": ",16,4,1,56,16,4,1,56,",
                "SInED": ",16,4,1,56,16,4,1,56,",
                "SInA": ",1,4,1,5,1,4,1,5,",
                "beatsInMeasure": "4",
                "songKey": "Db",
                "isPrivate": "0",
                "views": 0,
                "hasMelody": "1",
                "hasChords": "1",
                "isAnalysis": 0,
                "voteup": 0,
                "votedown": 0,
                "score": 0,
                "songURL": "helicopter",
                "artistURL": "oh-land",
                "sectionURL": "verse",
                "editComments": "",
                "visible": 1,
                "wikiorder": 1,
                "bIsPaired": 0,
                "YouTubeVideoID": null,
                "bpm": 90,
                "mode": 1,
                "borrowedFixed": "0",
                "SInEDFixed": "0",
                "user_id_editor": 39251
            },
            "main_data_type": "xml",
            "main_data": {
                "theorytab": {
                    "version": "1.2",
                    "meta": {
                        "artist": null,
                        "title": "Helicopter - Verse",
                        "beats_in_measure": "4",
                        "BPM": "90",
                        "key": "Db",
                        "YouTubeID": "SF8s8-6IXJM",
                        "mode": "1",
                        "band": {
                            "lead": {
                                "member": {
                                    "name": "Piano",
                                    "velocity": "0.8",
                                    "octaveOffset": "0",
                                    "mute": "false"
                                }
                            },
                            "lead2": null,
                            "lead3": null,
                            "lead4": null,
                            "harmony": {
                                "member": {
                                    "name": "Piano 1/4s",
                                    "velocity": "0.8",
                                    "octaveOffset": "0",
                                    "mute": "false"
                                }
                            },
                            "bass": {
                                "member": {
                                    "name": "Piano Bass Dotted",
                                    "velocity": "0.8",
                                    "octaveOffset": "0",
                                    "mute": "false"
                                }
                            },
                            "drums": null
                        },
                        "global_start": "2.4",
                        "duration": "16.23",
                        "active_start": "2.71",
                        "active_stop": "13.53"
                    },
                    "data": {
                        "segment": {
                            "melody": {
                                "voice": [
                                    {
                                        "lyrics": null,
                                        "notes": {
                                            "note": [
                                                {
                                                    "start_beat_abs": "0",
                                                    "start_measure": "1",
                                                    "start_beat": "1",
                                                    "note_length": "0.75",
                                                    "scale_degree": "5",
                                                    "octave": "-1",
                                                    "isRest": "0"
                                                },
                                                {
                                                    "start_beat_abs": "0.75",
                                                    "start_measure": "1",
                                                    "start_beat": "1.75",
                                                    "note_length": "0.75",
                                                    "scale_degree": "5",
                                                    "octave": "-1",
                                                    "isRest": "0"
                                                },
                                                {
                                                    "start_beat_abs": "1.5",
                                                    "start_measure": "1",
                                                    "start_beat": "2.5",
                                                    "note_length": "0.5",
                                                    "scale_degree": "6",
                                                    "octave": "-1",
                                                    "isRest": "0"
                                                },
                                                {
                                                    "start_beat_abs": "2",
                                                    "start_measure": "1",
                                                    "start_beat": "3",
                                                    "note_length": "1",
                                                    "scale_degree": "6",
                                                    "octave": "-1",
                                                    "isRest": "0"
                                                },
                                                {
                                                    "start_beat_abs": "3",
                                                    "start_measure": "1",
                                                    "start_beat": "4",
                                                    "note_length": "1",
                                                    "scale_degree": "6",
                                                    "octave": "-1",
                                                    "isRest": "0"
                                                },
                                                {
                                                    "start_beat_abs": "4",
                                                    "start_measure": "2",
                                                    "start_beat": "1",
                                                    "note_length": "1",
                                                    "scale_degree": "rest",
                                                    "octave": "0",
                                                    "isRest": "1"
                                                },
                                                {
                                                    "start_beat_abs": "5",
                                                    "start_measure": "2",
                                                    "start_beat": "2",
                                                    "note_length": "0.5",
                                                    "scale_degree": "5",
                                                    "octave": "-1",
                                                    "isRest": "0"
                                                },
                                                {
                                                    "start_beat_abs": "5.5",
                                                    "start_measure": "2",
                                                    "start_beat": "2.5",
                                                    "note_length": "0.5",
                                                    "scale_degree": "6",
                                                    "octave": "-1",
                                                    "isRest": "0"
                                                },
                                                {
                                                    "start_beat_abs": "6",
                                                    "start_measure": "2",
                                                    "start_beat": "3",
                                                    "note_length": "1",
                                                    "scale_degree": "1",
                                                    "octave": "0",
                                                    "isRest": "0"
                                                },
                                                {
                                                    "start_beat_abs": "7",
                                                    "start_measure": "2",
                                                    "start_beat": "4",
                                                    "note_length": "1",
                                                    "scale_degree": "2",
                                                    "octave": "0",
                                                    "isRest": "0"
                                                },
                                                {
                                                    "start_beat_abs": "8",
                                                    "start_measure": "3",
                                                    "start_beat": "1",
                                                    "note_length": "0.75",
                                                    "scale_degree": "5",
                                                    "octave": "-1",
                                                    "isRest": "0"
                                                },
                                                {
                                                    "start_beat_abs": "8.75",
                                                    "start_measure": "3",
                                                    "start_beat": "1.75",
                                                    "note_length": "0.75",
                                                    "scale_degree": "5",
                                                    "octave": "-1",
                                                    "isRest": "0"
                                                },
                                                {
                                                    "start_beat_abs": "9.5",
                                                    "start_measure": "3",
                                                    "start_beat": "2.5",
                                                    "note_length": "0.5",
                                                    "scale_degree": "6",
                                                    "octave": "-1",
                                                    "isRest": "0"
                                                },
                                                {
                                                    "start_beat_abs": "10",
                                                    "start_measure": "3",
                                                    "start_beat": "3",
                                                    "note_length": "1",
                                                    "scale_degree": "6",
                                                    "octave": "-1",
                                                    "isRest": "0"
                                                },
                                                {
                                                    "start_beat_abs": "11",
                                                    "start_measure": "3",
                                                    "start_beat": "4",
                                                    "note_length": "1",
                                                    "scale_degree": "6",
                                                    "octave": "-1",
                                                    "isRest": "0"
                                                },
                                                {
                                                    "start_beat_abs": "12",
                                                    "start_measure": "4",
                                                    "start_beat": "1",
                                                    "note_length": "0.5",
                                                    "scale_degree": "rest",
                                                    "octave": "0",
                                                    "isRest": "1"
                                                },
                                                {
                                                    "start_beat_abs": "12.5",
                                                    "start_measure": "4",
                                                    "start_beat": "1.5",
                                                    "note_length": "0.5",
                                                    "scale_degree": "6",
                                                    "octave": "-1",
                                                    "isRest": "0"
                                                },
                                                {
                                                    "start_beat_abs": "13",
                                                    "start_measure": "4",
                                                    "start_beat": "2",
                                                    "note_length": "0.5",
                                                    "scale_degree": "5",
                                                    "octave": "-1",
                                                    "isRest": "0"
                                                },
                                                {
                                                    "start_beat_abs": "13.5",
                                                    "start_measure": "4",
                                                    "start_beat": "2.5",
                                                    "note_length": "0.5",
                                                    "scale_degree": "6",
                                                    "octave": "-1",
                                                    "isRest": "0"
                                                },
                                                {
                                                    "start_beat_abs": "14",
                                                    "start_measure": "4",
                                                    "start_beat": "3",
                                                    "note_length": "1",
                                                    "scale_degree": "1",
                                                    "octave": "0",
                                                    "isRest": "0"
                                                },
                                                {
                                                    "start_beat_abs": "15",
                                                    "start_measure": "4",
                                                    "start_beat": "4",
                                                    "note_length": "1",
                                                    "scale_degree": "2",
                                                    "octave": "0",
                                                    "isRest": "0"
                                                }
                                            ]
                                        }
                                    },
                                    {
                                        "lyrics": null,
                                        "notes": null
                                    },
                                    {
                                        "lyrics": null,
                                        "notes": null
                                    },
                                    {
                                        "lyrics": null,
                                        "notes": null
                                    }
                                ]
                            },
                            "harmony": {
                                "chord": [
                                    {
                                        "sd": "1",
                                        "fb": "6",
                                        "sec": null,
                                        "sus": null,
                                        "pedal": null,
                                        "alternate": null,
                                        "borrowed": null,
                                        "chord_duration": "1.5",
                                        "start_measure": "1",
                                        "start_beat": "1",
                                        "start_beat_abs": "0",
                                        "isRest": "0"
                                    },
                                    {
                                        "sd": "4",
                                        "fb": null,
                                        "sec": null,
                                        "sus": null,
                                        "pedal": null,
                                        "alternate": null,
                                        "borrowed": null,
                                        "chord_duration": "4.5",
                                        "start_measure": "1",
                                        "start_beat": "2.5",
                                        "start_beat_abs": "1.5",
                                        "isRest": "0"
                                    },
                                    {
                                        "sd": "1",
                                        "fb": null,
                                        "sec": null,
                                        "sus": null,
                                        "pedal": null,
                                        "alternate": null,
                                        "borrowed": null,
                                        "chord_duration": "1",
                                        "start_measure": "2",
                                        "start_beat": "3",
                                        "start_beat_abs": "6",
                                        "isRest": "0"
                                    },
                                    {
                                        "sd": "5",
                                        "fb": "6",
                                        "sec": null,
                                        "sus": null,
                                        "pedal": null,
                                        "alternate": null,
                                        "borrowed": null,
                                        "chord_duration": "1",
                                        "start_measure": "2",
                                        "start_beat": "4",
                                        "start_beat_abs": "7",
                                        "isRest": "0"
                                    },
                                    {
                                        "sd": "1",
                                        "fb": "6",
                                        "sec": null,
                                        "sus": null,
                                        "pedal": null,
                                        "alternate": null,
                                        "borrowed": null,
                                        "chord_duration": "1.5",
                                        "start_measure": "3",
                                        "start_beat": "1",
                                        "start_beat_abs": "8",
                                        "isRest": "0"
                                    },
                                    {
                                        "sd": "4",
                                        "fb": null,
                                        "sec": null,
                                        "sus": null,
                                        "pedal": null,
                                        "alternate": null,
                                        "borrowed": null,
                                        "chord_duration": "4.5",
                                        "start_measure": "3",
                                        "start_beat": "2.5",
                                        "start_beat_abs": "9.5",
                                        "isRest": "0"
                                    },
                                    {
                                        "sd": "1",
                                        "fb": null,
                                        "sec": null,
                                        "sus": null,
                                        "pedal": null,
                                        "alternate": null,
                                        "borrowed": null,
                                        "chord_duration": "1",
                                        "start_measure": "4",
                                        "start_beat": "3",
                                        "start_beat_abs": "14",
                                        "isRest": "0"
                                    },
                                    {
                                        "sd": "5",
                                        "fb": "6",
                                        "sec": null,
                                        "sus": null,
                                        "pedal": null,
                                        "alternate": null,
                                        "borrowed": null,
                                        "chord_duration": "1",
                                        "start_measure": "4",
                                        "start_beat": "4",
                                        "start_beat_abs": "15",
                                        "isRest": "0"
                                    }
                                ]
                            },
                            "numMeasures": "4"
                        }
                    }
                }
            }
        },
        {
            "song_part_id": "lamkyjzvxDM",
            "metadata": {
                "ID": 223045,
                "user_id": 103696,
                "dateModified": "2015-11-04 14:29:27+00:00",
                "HTID": "VK2tkaf-lKAY",
                "artist": "Oh Land",
                "song": "Helicopter",
                "section": "Chorus",
                "revision": 0,
                "chords": null,
                "youTubeID": "SF8s8-6IXJM",
                "dotDNAbin": null,
                "xmlType": "file",
                "SIF": ",6-2,1-2,2-2,4-2,365-2,56-2/6,6-1,56-1,1-2,",
                "SInE": ",6-2,1-2,2-2,4-2,365-2,56-2/6,6-1,56-1,1-2,",
                "SInD": ",6,1,2,4,365,56/6,6,56,1,",
                "SInED": ",6,1,2,4,365,56/6,6,56,1,",
                "SInA": ",6,1,2,4,3,5/6,6,5,1,",
                "beatsInMeasure": "4",
                "songKey": "Db",
                "isPrivate": "0",
                "views": 0,
                "hasMelody": "1",
                "hasChords": "1",
                "isAnalysis": 0,
                "voteup": 0,
                "votedown": 0,
                "score": 0,
                "songURL": "helicopter",
                "artistURL": "oh-land",
                "sectionURL": "chorus",
                "editComments": "",
                "visible": 1,
                "wikiorder": 1,
                "bIsPaired": 0,
                "YouTubeVideoID": null,
                "bpm": 90,
                "mode": 1,
                "borrowedFixed": "0",
                "SInEDFixed": "0",
                "user_id_editor": 39251
            },
            "main_data_type": "xml",
            "main_data": {
                "theorytab": {
                    "version": "1.2",
                    "meta": {
                        "artist": null,
                        "title": "Helicopter - Chorus",
                        "beats_in_measure": "4",
                        "BPM": "90",
                        "key": "Db",
                        "YouTubeID": "SF8s8-6IXJM",
                        "mode": "1",
                        "band": {
                            "lead": {
                                "member": {
                                    "name": "Piano",
                                    "velocity": "0.8",
                                    "octaveOffset": "0",
                                    "mute": "false"
                                }
                            },
                            "lead2": null,
                            "lead3": null,
                            "lead4": null,
                            "harmony": {
                                "member": {
                                    "name": "Piano 1/4s",
                                    "velocity": "0.8",
                                    "octaveOffset": "0",
                                    "mute": "false"
                                }
                            },
                            "bass": {
                                "member": {
                                    "name": "Piano Bass Dotted",
                                    "velocity": "0.8",
                                    "octaveOffset": "0",
                                    "mute": "false"
                                }
                            },
                            "drums": null
                        },
                        "global_start": "34.59",
                        "duration": "15.96",
                        "active_start": "2.66",
                        "active_stop": "13.3"
                    },
                    "data": {
                        "segment": {
                            "melody": {
                                "voice": [
                                    {
                                        "lyrics": null,
                                        "notes": {
                                            "note": [
                                                {
                                                    "start_beat_abs": "0",
                                                    "start_measure": "1",
                                                    "start_beat": "1",
                                                    "note_length": "1",
                                                    "scale_degree": "1",
                                                    "octave": "0",
                                                    "isRest": "0"
                                                },
                                                {
                                                    "start_beat_abs": "1",
                                                    "start_measure": "1",
                                                    "start_beat": "2",
                                                    "note_length": "1",
                                                    "scale_degree": "1",
                                                    "octave": "1",
                                                    "isRest": "0"
                                                },
                                                {
                                                    "start_beat_abs": "2",
                                                    "start_measure": "1",
                                                    "start_beat": "3",
                                                    "note_length": "1",
                                                    "scale_degree": "7",
                                                    "octave": "0",
                                                    "isRest": "0"
                                                },
                                                {
                                                    "start_beat_abs": "3",
                                                    "start_measure": "1",
                                                    "start_beat": "4",
                                                    "note_length": "1",
                                                    "scale_degree": "3",
                                                    "octave": "0",
                                                    "isRest": "0"
                                                },
                                                {
                                                    "start_beat_abs": "4",
                                                    "start_measure": "2",
                                                    "start_beat": "1",
                                                    "note_length": "1",
                                                    "scale_degree": "5",
                                                    "octave": "0",
                                                    "isRest": "0"
                                                },
                                                {
                                                    "start_beat_abs": "5",
                                                    "start_measure": "2",
                                                    "start_beat": "2",
                                                    "note_length": "1",
                                                    "scale_degree": "4",
                                                    "octave": "0",
                                                    "isRest": "0"
                                                },
                                                {
                                                    "start_beat_abs": "6",
                                                    "start_measure": "2",
                                                    "start_beat": "3",
                                                    "note_length": "1",
                                                    "scale_degree": "6",
                                                    "octave": "-1",
                                                    "isRest": "0"
                                                },
                                                {
                                                    "start_beat_abs": "7",
                                                    "start_measure": "2",
                                                    "start_beat": "4",
                                                    "note_length": "1",
                                                    "scale_degree": "1",
                                                    "octave": "0",
                                                    "isRest": "0"
                                                },
                                                {
                                                    "start_beat_abs": "8",
                                                    "start_measure": "3",
                                                    "start_beat": "1",
                                                    "note_length": "1",
                                                    "scale_degree": "3",
                                                    "octave": "0",
                                                    "isRest": "0"
                                                },
                                                {
                                                    "start_beat_abs": "9",
                                                    "start_measure": "3",
                                                    "start_beat": "2",
                                                    "note_length": "1",
                                                    "scale_degree": "3",
                                                    "octave": "0",
                                                    "isRest": "0"
                                                },
                                                {
                                                    "start_beat_abs": "10",
                                                    "start_measure": "3",
                                                    "start_beat": "3",
                                                    "note_length": "1",
                                                    "scale_degree": "3",
                                                    "octave": "0",
                                                    "isRest": "0"
                                                },
                                                {
                                                    "start_beat_abs": "11",
                                                    "start_measure": "3",
                                                    "start_beat": "4",
                                                    "note_length": "1",
                                                    "scale_degree": "2",
                                                    "octave": "0",
                                                    "isRest": "0"
                                                },
                                                {
                                                    "start_beat_abs": "12",
                                                    "start_measure": "4",
                                                    "start_beat": "1",
                                                    "note_length": "1",
                                                    "scale_degree": "1",
                                                    "octave": "0",
                                                    "isRest": "0"
                                                },
                                                {
                                                    "start_beat_abs": "13",
                                                    "start_measure": "4",
                                                    "start_beat": "2",
                                                    "note_length": "1",
                                                    "scale_degree": "7",
                                                    "octave": "-1",
                                                    "isRest": "0"
                                                },
                                                {
                                                    "start_beat_abs": "14",
                                                    "start_measure": "4",
                                                    "start_beat": "3",
                                                    "note_length": "0.75",
                                                    "scale_degree": "1",
                                                    "octave": "0",
                                                    "isRest": "0"
                                                },
                                                {
                                                    "start_beat_abs": "14.75",
                                                    "start_measure": "4",
                                                    "start_beat": "3.75",
                                                    "note_length": "0.25",
                                                    "scale_degree": "2",
                                                    "octave": "0",
                                                    "isRest": "0"
                                                },
                                                {
                                                    "start_beat_abs": "15",
                                                    "start_measure": "4",
                                                    "start_beat": "4",
                                                    "note_length": "0.25",
                                                    "scale_degree": "3",
                                                    "octave": "0",
                                                    "isRest": "0"
                                                },
                                                {
                                                    "start_beat_abs": "15.25",
                                                    "start_measure": "4",
                                                    "start_beat": "4.25",
                                                    "note_length": "0.25",
                                                    "scale_degree": "4",
                                                    "octave": "0",
                                                    "isRest": "0"
                                                },
                                                {
                                                    "start_beat_abs": "15.5",
                                                    "start_measure": "4",
                                                    "start_beat": "4.5",
                                                    "note_length": "0.5",
                                                    "scale_degree": "3",
                                                    "octave": "0",
                                                    "isRest": "0"
                                                }
                                            ]
                                        }
                                    },
                                    {
                                        "lyrics": null,
                                        "notes": null
                                    },
                                    {
                                        "lyrics": null,
                                        "notes": null
                                    },
                                    {
                                        "lyrics": null,
                                        "notes": null
                                    }
                                ]
                            },
                            "harmony": {
                                "chord": [
                                    {
                                        "sd": "6",
                                        "fb": null,
                                        "sec": null,
                                        "sus": null,
                                        "pedal": null,
                                        "alternate": null,
                                        "borrowed": null,
                                        "chord_duration": "2",
                                        "start_measure": "1",
                                        "start_beat": "1",
                                        "start_beat_abs": "0",
                                        "isRest": "0"
                                    },
                                    {
                                        "sd": "1",
                                        "fb": null,
                                        "sec": null,
                                        "sus": null,
                                        "pedal": null,
                                        "alternate": null,
                                        "borrowed": null,
                                        "chord_duration": "2",
                                        "start_measure": "1",
                                        "start_beat": "3",
                                        "start_beat_abs": "2",
                                        "isRest": "0"
                                    },
                                    {
                                        "sd": "2",
                                        "fb": null,
                                        "sec": null,
                                        "sus": null,
                                        "pedal": null,
                                        "alternate": null,
                                        "borrowed": null,
                                        "chord_duration": "2",
                                        "start_measure": "2",
                                        "start_beat": "1",
                                        "start_beat_abs": "4",
                                        "isRest": "0"
                                    },
                                    {
                                        "sd": "4",
                                        "fb": null,
                                        "sec": null,
                                        "sus": null,
                                        "pedal": null,
                                        "alternate": null,
                                        "borrowed": null,
                                        "chord_duration": "2",
                                        "start_measure": "2",
                                        "start_beat": "3",
                                        "start_beat_abs": "6",
                                        "isRest": "0"
                                    },
                                    {
                                        "sd": "3",
                                        "fb": "65",
                                        "sec": null,
                                        "sus": null,
                                        "pedal": null,
                                        "alternate": null,
                                        "borrowed": null,
                                        "chord_duration": "2",
                                        "start_measure": "3",
                                        "start_beat": "1",
                                        "start_beat_abs": "8",
                                        "isRest": "0"
                                    },
                                    {
                                        "sd": "5",
                                        "fb": "6",
                                        "sec": "6",
                                        "sus": null,
                                        "pedal": null,
                                        "alternate": null,
                                        "borrowed": null,
                                        "chord_duration": "2",
                                        "start_measure": "3",
                                        "start_beat": "3",
                                        "start_beat_abs": "10",
                                        "isRest": "0"
                                    },
                                    {
                                        "sd": "6",
                                        "fb": null,
                                        "sec": null,
                                        "sus": null,
                                        "pedal": null,
                                        "alternate": null,
                                        "borrowed": null,
                                        "chord_duration": "1",
                                        "start_measure": "4",
                                        "start_beat": "1",
                                        "start_beat_abs": "12",
                                        "isRest": "0"
                                    },
                                    {
                                        "sd": "5",
                                        "fb": "6",
                                        "sec": null,
                                        "sus": null,
                                        "pedal": null,
                                        "alternate": null,
                                        "borrowed": null,
                                        "chord_duration": "1",
                                        "start_measure": "4",
                                        "start_beat": "2",
                                        "start_beat_abs": "13",
                                        "isRest": "0"
                                    },
                                    {
                                        "sd": "1",
                                        "fb": null,
                                        "sec": null,
                                        "sus": null,
                                        "pedal": null,
                                        "alternate": null,
                                        "borrowed": null,
                                        "chord_duration": "2",
                                        "start_measure": "4",
                                        "start_beat": "3",
                                        "start_beat_abs": "14",
                                        "isRest": "0"
                                    }
                                ]
                            },
                            "numMeasures": "4"
                        }
                    }
                }
            }
        },
        {
            "song_part_id": "kygzRqPzgKB",
            "metadata": {
                "ID": 223043,
                "user_id": 103696,
                "dateModified": "2015-11-04 14:28:03+00:00",
                "HTID": "lRIqWncQrlPe",
                "artist": "Oh Land",
                "song": "Helicopter",
                "section": "Bridge",
                "revision": 0,
                "chords": null,
                "youTubeID": "SF8s8-6IXJM",
                "dotDNAbin": null,
                "xmlType": "file",
                "SIF": ",4-1,5-1,6-2,b7-4,b5-4,L2-4,b3-2,L2-2,b7-4,b5-4,L2-4,b3-2,L2-2,",
                "SInE": ",4-1,5-1,6-2,b7-4,b5-4,L2-4,b3-2,L2-2,b7-4,b5-4,L2-4,b3-2,L2-2,",
                "SInD": ",4,5,6,b7,b5,L2,b3,L2,b7,b5,L2,b3,L2,",
                "SInED": ",4,5,6,b7,b5,L2,b3,L2,b7,b5,L2,b3,L2,",
                "SInA": ",4,5,6,b7,b5,L2,b3,L2,b7,b5,L2,b3,L2,",
                "beatsInMeasure": "4",
                "songKey": "Db",
                "isPrivate": "0",
                "views": 0,
                "hasMelody": "0",
                "hasChords": "1",
                "isAnalysis": 0,
                "voteup": 0,
                "votedown": 0,
                "score": 0,
                "songURL": "helicopter",
                "artistURL": "oh-land",
                "sectionURL": "bridge",
                "editComments": "",
                "visible": 1,
                "wikiorder": 1,
                "bIsPaired": 0,
                "YouTubeVideoID": null,
                "bpm": 89,
                "mode": 1,
                "borrowedFixed": "0",
                "SInEDFixed": "0",
                "user_id_editor": 39251
            },
            "main_data_type": "xml",
            "main_data": {
                "theorytab": {
                    "version": "1.2",
                    "meta": {
                        "artist": null,
                        "title": "Helicopter - Bridge",
                        "beats_in_measure": "4",
                        "BPM": "89",
                        "key": "Db",
                        "YouTubeID": "SF8s8-6IXJM",
                        "mode": "1",
                        "band": {
                            "lead": {
                                "member": {
                                    "name": "Piano",
                                    "velocity": "0.8",
                                    "octaveOffset": "0",
                                    "mute": "false"
                                }
                            },
                            "lead2": null,
                            "lead3": null,
                            "lead4": null,
                            "harmony": {
                                "member": {
                                    "name": "Piano 1/4s",
                                    "velocity": "0.8",
                                    "octaveOffset": "0",
                                    "mute": "false"
                                }
                            },
                            "bass": {
                                "member": {
                                    "name": "Piano Bass Dotted",
                                    "velocity": "0.8",
                                    "octaveOffset": "0",
                                    "mute": "false"
                                }
                            },
                            "drums": null
                        },
                        "global_start": "114.54",
                        "duration": "29.42",
                        "active_start": "2.67",
                        "active_stop": "26.75"
                    },
                    "data": {
                        "segment": [
                            {
                                "melody": {
                                    "voice": [
                                        {
                                            "lyrics": null,
                                            "notes": null
                                        },
                                        {
                                            "lyrics": null,
                                            "notes": null
                                        },
                                        {
                                            "lyrics": null,
                                            "notes": null
                                        },
                                        {
                                            "lyrics": null,
                                            "notes": null
                                        }
                                    ]
                                },
                                "harmony": {
                                    "chord": [
                                        {
                                            "sd": "4",
                                            "fb": null,
                                            "sec": null,
                                            "sus": null,
                                            "pedal": null,
                                            "alternate": null,
                                            "borrowed": null,
                                            "chord_duration": "1",
                                            "start_measure": "1",
                                            "start_beat": "1",
                                            "start_beat_abs": "0",
                                            "isRest": "0"
                                        },
                                        {
                                            "sd": "5",
                                            "fb": null,
                                            "sec": null,
                                            "sus": null,
                                            "pedal": null,
                                            "alternate": null,
                                            "borrowed": null,
                                            "chord_duration": "1",
                                            "start_measure": "1",
                                            "start_beat": "2",
                                            "start_beat_abs": "1",
                                            "isRest": "0"
                                        },
                                        {
                                            "sd": "6",
                                            "fb": null,
                                            "sec": null,
                                            "sus": null,
                                            "pedal": null,
                                            "alternate": null,
                                            "borrowed": null,
                                            "chord_duration": "2",
                                            "start_measure": "1",
                                            "start_beat": "3",
                                            "start_beat_abs": "2",
                                            "isRest": "0"
                                        },
                                        {
                                            "sd": "7",
                                            "fb": null,
                                            "sec": null,
                                            "sus": null,
                                            "pedal": null,
                                            "alternate": null,
                                            "borrowed": "-3",
                                            "chord_duration": "4",
                                            "start_measure": "2",
                                            "start_beat": "1",
                                            "start_beat_abs": "4",
                                            "isRest": "0"
                                        },
                                        {
                                            "sd": "5",
                                            "fb": null,
                                            "sec": null,
                                            "sus": null,
                                            "pedal": null,
                                            "alternate": null,
                                            "borrowed": "-3",
                                            "chord_duration": "4",
                                            "start_measure": "3",
                                            "start_beat": "1",
                                            "start_beat_abs": "8",
                                            "isRest": "0"
                                        },
                                        {
                                            "sd": "2",
                                            "fb": null,
                                            "sec": null,
                                            "sus": null,
                                            "pedal": null,
                                            "alternate": null,
                                            "borrowed": "1",
                                            "chord_duration": "4",
                                            "start_measure": "4",
                                            "start_beat": "1",
                                            "start_beat_abs": "12",
                                            "isRest": "0"
                                        },
                                        {
                                            "sd": "3",
                                            "fb": null,
                                            "sec": null,
                                            "sus": null,
                                            "pedal": null,
                                            "alternate": null,
                                            "borrowed": "-3",
                                            "chord_duration": "2",
                                            "start_measure": "5",
                                            "start_beat": "1",
                                            "start_beat_abs": "16",
                                            "isRest": "0"
                                        },
                                        {
                                            "sd": "2",
                                            "fb": null,
                                            "sec": null,
                                            "sus": null,
                                            "pedal": null,
                                            "alternate": null,
                                            "borrowed": "1",
                                            "chord_duration": "2",
                                            "start_measure": "5",
                                            "start_beat": "3",
                                            "start_beat_abs": "18",
                                            "isRest": "0"
                                        }
                                    ]
                                },
                                "numMeasures": "5"
                            },
                            {
                                "melody": {
                                    "voice": [
                                        {
                                            "lyrics": null,
                                            "notes": null
                                        },
                                        {
                                            "lyrics": null,
                                            "notes": null
                                        },
                                        {
                                            "lyrics": null,
                                            "notes": null
                                        },
                                        {
                                            "lyrics": null,
                                            "notes": null
                                        }
                                    ]
                                },
                                "harmony": {
                                    "chord": [
                                        {
                                            "sd": "7",
                                            "fb": null,
                                            "sec": null,
                                            "sus": null,
                                            "pedal": null,
                                            "alternate": null,
                                            "borrowed": "-3",
                                            "chord_duration": "4",
                                            "start_measure": "1",
                                            "start_beat": "1",
                                            "start_beat_abs": "0",
                                            "isRest": "0"
                                        },
                                        {
                                            "sd": "5",
                                            "fb": null,
                                            "sec": null,
                                            "sus": null,
                                            "pedal": null,
                                            "alternate": null,
                                            "borrowed": "-3",
                                            "chord_duration": "4",
                                            "start_measure": "2",
                                            "start_beat": "1",
                                            "start_beat_abs": "4",
                                            "isRest": "0"
                                        },
                                        {
                                            "sd": "2",
                                            "fb": null,
                                            "sec": null,
                                            "sus": null,
                                            "pedal": null,
                                            "alternate": null,
                                            "borrowed": "1",
                                            "chord_duration": "4",
                                            "start_measure": "3",
                                            "start_beat": "1",
                                            "start_beat_abs": "8",
                                            "isRest": "0"
                                        },
                                        {
                                            "sd": "3",
                                            "fb": null,
                                            "sec": null,
                                            "sus": null,
                                            "pedal": null,
                                            "alternate": null,
                                            "borrowed": "-3",
                                            "chord_duration": "2",
                                            "start_measure": "4",
                                            "start_beat": "1",
                                            "start_beat_abs": "12",
                                            "isRest": "0"
                                        },
                                        {
                                            "sd": "2",
                                            "fb": null,
                                            "sec": null,
                                            "sus": null,
                                            "pedal": null,
                                            "alternate": null,
                                            "borrowed": "1",
                                            "chord_duration": "2",
                                            "start_measure": "4",
                                            "start_beat": "3",
                                            "start_beat_abs": "14",
                                            "isRest": "0"
                                        }
                                    ]
                                },
                                "numMeasures": "4"
                            }
                        ]
                    }
                }
            }
        }
    ]
}