{
    "artist_name": "Project RnL",
    "artist_link": "https://www.hooktheory.com/theorytab/artists/p/project-rnl",
    "song_name": "The Avenger",
    "link": "https://www.hooktheory.com/theorytab/view/project-rnl/the-avenger",
    "metrics": {
        "Chord Complexity": "91",
        "Melodic Complexity": "66",
        "Chord-Melody Tension": "30",
        "Chord Progression Novelty": "93",
        "Chord Bass Melody": "60"
    },
    "metrics_conclusion": " In terms of chords and melody, The Avenger is more complex than the typical song, having above average scores in Chord Complexity, Melodic Complexity, Chord Progression Novelty and Chord-Bass Melody. ",
    "key_conclusion": " The Avenger has sections analyzed in the following keys: B Mixolydian,  and B Major.  Click on the linked cheat sheets for popular chords, chord progressions, downloadable midi files and more!",
    "song_parts_ids": [
        "ROmNzQKQmNw",
        "Dpgvdkvaoad",
        "DpgvlGEkoad"
    ]
}